odoo/addons/ssi_hr_award/README.rst
odoo/addons/ssi_hr_award/__init__.py
odoo/addons/ssi_hr_award/__manifest__.py
odoo/addons/ssi_hr_award/data/approval_template_data.xml
odoo/addons/ssi_hr_award/data/ir_sequence_data.xml
odoo/addons/ssi_hr_award/data/policy_template_data.xml
odoo/addons/ssi_hr_award/data/sequence_template_data.xml
odoo/addons/ssi_hr_award/i18n/id.po
odoo/addons/ssi_hr_award/i18n/ssi_hr_award.pot
odoo/addons/ssi_hr_award/models/__init__.py
odoo/addons/ssi_hr_award/models/hr_award.py
odoo/addons/ssi_hr_award/models/hr_award_reason.py
odoo/addons/ssi_hr_award/models/hr_award_type.py
odoo/addons/ssi_hr_award/security/ir.model.access.csv
odoo/addons/ssi_hr_award/security/ir_module_category_data.xml
odoo/addons/ssi_hr_award/security/ir_rule_data.xml
odoo/addons/ssi_hr_award/security/res_group_data.xml
odoo/addons/ssi_hr_award/static/description/icon.png
odoo/addons/ssi_hr_award/views/hr_award_reason_views.xml
odoo/addons/ssi_hr_award/views/hr_award_type_views.xml
odoo/addons/ssi_hr_award/views/hr_award_views.xml
odoo14_addon_ssi_hr_award-14.0.1.4.0.dist-info/METADATA
odoo14_addon_ssi_hr_award-14.0.1.4.0.dist-info/WHEEL
odoo14_addon_ssi_hr_award-14.0.1.4.0.dist-info/top_level.txt
odoo14_addon_ssi_hr_award-14.0.1.4.0.dist-info/RECORD
